{
  "version": "1.1.7-52a1d35-canary",
  "platforms": {
    "x86_64-linux": {
      "url": "https://atlasbinaries.com/atlas/atlas-linux-amd64-v1.1.7-52a1d35-canary",
      "sha256": "1d4xaiaj1i253c4ilhpx69k6dg006z5qm4zszcsh3swwyajilpw4"
    },
    "x86_64-darwin": {
      "url": "https://atlasbinaries.com/atlas/atlas-darwin-amd64-v1.1.7-52a1d35-canary",
      "sha256": "168qagbfkf344pmbnpmqf0lkjs2ik4zwwx66wavy9k9i2giq7dri"
    },
    "aarch64-darwin": {
      "url": "https://atlasbinaries.com/atlas/atlas-darwin-arm64-v1.1.7-52a1d35-canary",
      "sha256": "19298vq9y6wa19bpbrck60pz5n4jiivfhv9z40wizn71nf71amxz"
    }
  }
}
